LICENSE.txt
MANIFEST.in
README.rst
setup.cfg
setup.py
gorylla/__init__.py
gorylla/ex.py
gorylla/future.py
gorylla/mis.py
gorylla/tick.py
gorylla.egg-info/PKG-INFO
gorylla.egg-info/SOURCES.txt
gorylla.egg-info/dependency_links.txt
gorylla.egg-info/entry_points.txt
gorylla.egg-info/requires.txt
gorylla.egg-info/top_level.txt