Metadata-Version: 1.1
Name: gorylla
Version: 0.1.10.3
Summary: A gorylla Python project
Home-page: https://github.com/hzhijin/gorylla
Author: boyang
Author-email: liboooyang@gmail.com
License: MIT
Keywords: gorylla setuptools development
Platform: UNKNOWN
Classifier: Development Status :: 3 - Alpha
Classifier: Intended Audience :: Developers
Classifier: Topic :: Software Development :: Build Tools
Classifier: License :: OSI Approved :: MIT License
Classifier: Programming Language :: Python :: 3.5
